ad_main/__init__.py
ad_main/celeryapp.py
ad_main/settings.py
ad_main/test_settings.py
ad_main/urls.py
ad_main/wsgi.py
alertadengue-3.2.0.dist-info/LICENSE
alertadengue-3.2.0.dist-info/WHEEL
alertadengue-3.2.0.dist-info/METADATA
alertadengue-3.2.0.dist-info/RECORD
