Metadata-Version: 2.1
Name: alertadengue
Version: 3.2.0
Summary: AlertaDengue Package
Home-page: https://github.com/AlertaDengue/AlertaDengue
License: GNU General Public License v3
Author: Flavio Codeco Coelho
Author-email: fccoelho@gmail.com
Requires-Python: >=3.9,<3.11
Classifier: License :: Other/Proprietary License
Classifier: Programming Language :: Python :: 3
Classifier: Programming Language :: Python :: 3.9
Classifier: Programming Language :: Python :: 3.10
Requires-Dist: Django (>=3.1.8,<4)
Requires-Dist: celery (>=5.2.7,<6.0.0)
Requires-Dist: dbfread (>=2.0.7,<3.0.0)
Requires-Dist: dj-database-url (>=1.2.0,<2.0.0)
Requires-Dist: dj-static (>=0.0.6,<0.0.7)
Requires-Dist: django-bootstrap4 (>=22.3,<23.0)
Requires-Dist: django-celery-results (>=2.4.0,<3.0.0)
Requires-Dist: django-chunked-upload (>=2.0.0,<3.0.0)
Requires-Dist: django-cprofile-middleware (>=1.0.5,<2.0.0)
Requires-Dist: django-leaflet (>=0.28.3,<0.29.0)
Requires-Dist: django-maintenance-mode (>=0.18.0,<0.19.0)
Requires-Dist: django-pymemcache (>=1.0.0,<2.0.0)
Requires-Dist: docker-compose (>=1.29.2,<2.0.0)
Requires-Dist: fastparquet (>=2022.12.0,<2023.0.0)
Requires-Dist: fiona (>=1.8.22,<2.0.0)
Requires-Dist: geojson (>=2.5.0,<3.0.0)
Requires-Dist: geopandas (>=0.12.2,<0.13.0)
Requires-Dist: geopy (>=2.3.0,<3.0.0)
Requires-Dist: gunicorn (>=20.1.0,<21.0.0)
Requires-Dist: ibis-framework[postgres] (>=3.2.0,<4.0.0)
Requires-Dist: plotly (>=5.11.0,<6.0.0)
Requires-Dist: pyproj (>=3.4.1,<4.0.0)
Requires-Dist: python-dotenv (>=0.21.0,<0.22.0)
Requires-Dist: python-memcached (>=1.59,<2.0)
Requires-Dist: rasterio (>=1.3.4,<2.0.0)
Requires-Dist: simpledbf (>=0.2.6,<0.3.0)
Requires-Dist: tables (>=3.8.0,<4.0.0)
Project-URL: Repository, https://github.com/AlertaDengue/AlertaDengue
